setup.py
szuboard2feed/__init__.py
szuboard2feed/autologin.py
szuboard2feed/errors.py
szuboard2feed/fetchurl.py
szuboard2feed/genfeed.py
szuboard2feed/genfeednode.py
szuboard2feed.egg-info/PKG-INFO
szuboard2feed.egg-info/SOURCES.txt
szuboard2feed.egg-info/dependency_links.txt
szuboard2feed.egg-info/requires.txt
szuboard2feed.egg-info/top_level.txt