Metadata-Version: 1.0
Name: szuboard2feed
Version: 0.0.2
Summary: Convert SZUboard (Gongwentong) to feed.
Home-page: https://github.com/marknv/szuboard2feed
Author: MarkNV
Author-email: marknv1991@gmail.com
License: MIT License
Platform: UNKNOWN
